ahmpy/AhmCos.py
ahmpy/AhmEmail.py
ahmpy/AhmExcel.py
ahmpy/AhmMonitor.py
ahmpy/__init__.py
ahmpy-0.1.4.dist-info/METADATA
ahmpy-0.1.4.dist-info/WHEEL
ahmpy-0.1.4.dist-info/top_level.txt
ahmpy-0.1.4.dist-info/RECORD
