Metadata-Version: 2.1
Name: ahmpy
Version: 0.1.4
Summary: tools for ahm company
Author: nameingishard
Author-email: 2569674866@qq.com
Classifier: Programming Language :: Python :: 3
Classifier: License :: OSI Approved :: MIT License
Classifier: Operating System :: OS Independent
Requires-Python: >=3.6
Requires-Dist: cos-python-sdk-v5
Requires-Dist: openpyxl>=3.0.10
